gitbetter/__init__.py
gitbetter/git.py
gitbetter/gitbetter.py
gitbetter/parsers.py
gitbetter/py.typed
gitbetter-4.0.1.dist-info/METADATA
gitbetter-4.0.1.dist-info/WHEEL
gitbetter-4.0.1.dist-info/entry_points.txt
gitbetter-4.0.1.dist-info/licenses/LICENSE.txt
gitbetter-4.0.1.dist-info/RECORD
