Metadata-Version: 2.1
Name: gitbetter
Version: 4.0.1
Summary: Custom git shell to type less and commit more.
Project-URL: Homepage, https://github.com/matt-manes/gitbetter
Project-URL: Documentation, https://github.com/matt-manes/gitbetter/tree/main/docs
Project-URL: Source code, https://github.com/matt-manes/gitbetter/tree/main/src/gitbetter
Author-email: Matt Manes <mattmanes@pm.me>
License-File: LICENSE.txt
Keywords: cli,commit,git,shell,terminal
Classifier: License :: OSI Approved :: MIT License
Classifier: Operating System :: OS Independent
Classifier: Programming Language :: Python :: 3
Requires-Python: >=3.10
Requires-Dist: argshell
Requires-Dist: morbin
Requires-Dist: noiftimer
Requires-Dist: pathier
